arcade_slack/__init__.py
arcade_slack/constants.py
arcade_slack/conversation_retrieval.py
arcade_slack/critics.py
arcade_slack/custom_types.py
arcade_slack/exceptions.py
arcade_slack/message_retrieval.py
arcade_slack/models.py
arcade_slack/user_retrieval.py
arcade_slack/utils.py
arcade_slack/who_am_i_util.py
arcade_slack/tools/__init__.py
arcade_slack/tools/chat.py
arcade_slack/tools/system_context.py
arcade_slack/tools/users.py
arcade_slack-1.2.1.dist-info/METADATA
arcade_slack-1.2.1.dist-info/WHEEL
arcade_slack-1.2.1.dist-info/licenses/LICENSE
arcade_slack-1.2.1.dist-info/RECORD
