Metadata-Version: 2.4
Name: arcade_slack
Version: 1.2.1
Summary: Arcade.dev LLM tools for Slack
Author-email: Arcade <dev@arcade.dev>
License: Proprietary - Arcade Software License Agreement v1.0
License-File: LICENSE
Requires-Python: >=3.10
Requires-Dist: aiodns<2.0.0,>=1.0
Requires-Dist: aiohttp<4.0.0,>=3.7.3
Requires-Dist: arcade-tdk<4.0.0,>=3.0.0
Requires-Dist: slack-sdk<4.0.0,>=3.31.0
Requires-Dist: typing; python_version < '3.7'
Provides-Extra: dev
Requires-Dist: arcade-mcp[evals]<2.0.0,>=1.1.0; extra == 'dev'
Requires-Dist: arcade-serve<4.0.0,>=3.0.0; extra == 'dev'
Requires-Dist: mypy<1.6.0,>=1.5.1; extra == 'dev'
Requires-Dist: pre-commit<3.5.0,>=3.4.0; extra == 'dev'
Requires-Dist: pytest-asyncio<0.25.0,>=0.24.0; extra == 'dev'
Requires-Dist: pytest-cov<4.1.0,>=4.0.0; extra == 'dev'
Requires-Dist: pytest-mock<3.12.0,>=3.11.1; extra == 'dev'
Requires-Dist: pytest<8.4.0,>=8.3.0; extra == 'dev'
Requires-Dist: ruff<0.8.0,>=0.7.4; extra == 'dev'
Requires-Dist: tox<4.12.0,>=4.11.1; extra == 'dev'
